__init__.py
novel_swarms/__init__.py
novel_swarms/agent/Agent.py
novel_swarms/agent/AgentFactory.py
novel_swarms/agent/DiffDriveAgent.py
novel_swarms/agent/DroneAgent.py
novel_swarms/agent/HumanAgent.py
novel_swarms/agent/LevyAgent.py
novel_swarms/agent/MazeAgent.py
novel_swarms/agent/ModeSwitchingAgent.py
novel_swarms/agent/StaticAgent.py
novel_swarms/agent/UnicycleAgent.py
novel_swarms/agent/__init__.py
novel_swarms/behavior/AbstractBehavior.py
novel_swarms/behavior/AgentsAtGoal.py
novel_swarms/behavior/AlgebraicConnectivity.py
novel_swarms/behavior/AngularMomentum.py
novel_swarms/behavior/AverageSpeed.py
novel_swarms/behavior/BehaviorFactory.py
novel_swarms/behavior/Centroid.py
novel_swarms/behavior/ConvexHull.py
novel_swarms/behavior/DistanceToGoal.py
novel_swarms/behavior/GroupRotationBehavior.py
novel_swarms/behavior/PersistentHomology.py
novel_swarms/behavior/RadialVariance.py
novel_swarms/behavior/ScatterBehavior.py
novel_swarms/behavior/SensorOffset.py
novel_swarms/behavior/SensorRotation.py
novel_swarms/behavior/SensorSignal.py
novel_swarms/behavior/SubGroupWrapper.py
novel_swarms/behavior/TotalCollisions.py
novel_swarms/behavior/__init__.py
novel_swarms/cache/ExternalSimulationArchive.py
novel_swarms/cache/__init__.py
novel_swarms/config/AgentConfig.py
novel_swarms/config/EvolutionaryConfig.py
novel_swarms/config/HeterogenSwarmConfig.py
novel_swarms/config/ModeConfig.py
novel_swarms/config/OutputTensorConfig.py
novel_swarms/config/ResultsConfig.py
novel_swarms/config/WorldConfig.py
novel_swarms/config/__init__.py
novel_swarms/config/defaults.py
novel_swarms/gui/__init__.py
novel_swarms/gui/abstractGUI.py
novel_swarms/gui/agentGUI.py
novel_swarms/gui/connectivityGUI.py
novel_swarms/gui/controllerGUI.py
novel_swarms/gui/evolutionGUI.py
novel_swarms/novelty/BehaviorDiscovery.py
novel_swarms/novelty/GeneRule.py
novel_swarms/novelty/NoveltyArchive.py
novel_swarms/novelty/__init__.py
novel_swarms/novelty/evolve.py
novel_swarms/optim/CMAES.py
novel_swarms-0.1.9a0.dist-info/LICENSE
novel_swarms-0.1.9a0.dist-info/METADATA
novel_swarms-0.1.9a0.dist-info/WHEEL
novel_swarms-0.1.9a0.dist-info/top_level.txt
novel_swarms-0.1.9a0.dist-info/RECORD
