Metadata-Version: 2.1
Name: novel-swarms
Version: 0.1.9a0
Summary: A Swarm Simulation Package
Author-email: Connor Mattson <c.mattson@utah.edu>
Project-URL: Homepage, https://github.com/Connor-Mattson/RobotSwarmSimulator
Project-URL: Bug Tracker, https://github.com/Connor-Mattson/RobotSwarmSimulator/issues
Classifier: Programming Language :: Python :: 3
Classifier: License :: OSI Approved :: MIT License
Classifier: Operating System :: OS Independent
Requires-Python: >=3.7
License-File: LICENSE
